nnpack/__init__.py
nnpack/models.py
nnpack/scaffolds.py
nnpack/engines/__init__.py
nnpack/engines/_tensorflow.py
nnpack-0.1.0.dist-info/DESCRIPTION.rst
nnpack-0.1.0.dist-info/METADATA
nnpack-0.1.0.dist-info/RECORD
nnpack-0.1.0.dist-info/WHEEL
nnpack-0.1.0.dist-info/metadata.json
nnpack-0.1.0.dist-info/top_level.txt
