Metadata-Version: 2.0
Name: nnpack
Version: 0.1.0
Summary: Packaging and Data Portability for Neural Networks
Home-page: https://github.com/dominiek/nnpack
Author: UNKNOWN
Author-email: UNKNOWN
License: UNKNOWN
Platform: UNKNOWN
